odoo/addons/somalimentacio/__init__.py
odoo/addons/somalimentacio/__manifest__.py
odoo/addons/somalimentacio/i18n/ca_ES.po
odoo/addons/somalimentacio/i18n/es.po
odoo/addons/somalimentacio/views/subscription_template.xml
odoo_addon_somalimentacio-16.0.1.0.0.2.dist-info/METADATA
odoo_addon_somalimentacio-16.0.1.0.0.2.dist-info/WHEEL
odoo_addon_somalimentacio-16.0.1.0.0.2.dist-info/top_level.txt
odoo_addon_somalimentacio-16.0.1.0.0.2.dist-info/RECORD
