Metadata-Version: 2.1
Name: odoo-addon-somalimentacio
Version: 16.0.1.0.0.2
Requires-Python: >=3.10
Requires-Dist: odoo-addon-cooperator_website>=16.0dev,<16.1dev
Requires-Dist: odoo>=16.0a,<16.1dev
Summary: Odoo Somalimentacio customizations
Home-page: https://coopdevs.org
License: AGPL-3
Author: Coopdevs Treball SCCL
Classifier: Programming Language :: Python
Classifier: Framework :: Odoo
Classifier: Framework :: Odoo :: 16.0
Classifier: License :: OSI Approved :: GNU Affero General Public License v3
